_kyber_kyber1024.pyd
_kyber_kyber512.pyd
_kyber_kyber768.pyd
kybercffi/__init__.py
kybercffi/_build_cffi.py
kybercffi/_kyber_kyber1024.c
kybercffi/_kyber_kyber512.c
kybercffi/_kyber_kyber768.c
kybercffi/kyber.py
kybercffi/Release/_kyber_kyber1024.cp312-win_amd64.exp
kybercffi/Release/_kyber_kyber512.cp312-win_amd64.exp
kybercffi/Release/_kyber_kyber768.cp312-win_amd64.exp
kybercffi/Release/Users/Jaykart/Downloads/Kyber-clear/Kyber-clear/kyber/ref/_kyber_kyber1024.cp312-win_amd64.exp
kybercffi/Release/Users/Jaykart/Downloads/Kyber-clear/Kyber-clear/kyber/ref/_kyber_kyber512.cp312-win_amd64.exp
kybercffi/Release/Users/Jaykart/Downloads/Kyber-clear/Kyber-clear/kyber/ref/_kyber_kyber768.cp312-win_amd64.exp
kybercffi/Release/kyber/ref/_kyber_kyber1024.cp312-win_amd64.exp
kybercffi/Release/kyber/ref/_kyber_kyber512.cp312-win_amd64.exp
kybercffi/Release/kyber/ref/_kyber_kyber768.cp312-win_amd64.exp
kybercffi/kyber/.gitattributes
kybercffi/kyber/.gitignore
kybercffi/kyber/.travis.yml
kybercffi/kyber/AUTHORS
kybercffi/kyber/Common_META.yml
kybercffi/kyber/Kyber1024_META.yml
kybercffi/kyber/Kyber512_META.yml
kybercffi/kyber/Kyber768_META.yml
kybercffi/kyber/LICENSE
kybercffi/kyber/README.md
kybercffi/kyber/SHA256SUMS
kybercffi/kyber/runlcov.sh
kybercffi/kyber/Release/_kyber.cp312-win_amd64.exp
kybercffi/kyber/Release/_kyber_simple.cp312-win_amd64.exp
kybercffi/kyber/avx2/.gitignore
kybercffi/kyber/avx2/Makefile
kybercffi/kyber/avx2/align.h
kybercffi/kyber/avx2/api.h
kybercffi/kyber/avx2/basemul.S
kybercffi/kyber/avx2/cbd.c
kybercffi/kyber/avx2/cbd.h
kybercffi/kyber/avx2/consts.c
kybercffi/kyber/avx2/consts.h
kybercffi/kyber/avx2/fips202.c
kybercffi/kyber/avx2/fips202.h
kybercffi/kyber/avx2/fips202x4.c
kybercffi/kyber/avx2/fips202x4.h
kybercffi/kyber/avx2/fq.S
kybercffi/kyber/avx2/fq.inc
kybercffi/kyber/avx2/indcpa.c
kybercffi/kyber/avx2/indcpa.h
kybercffi/kyber/avx2/invntt.S
kybercffi/kyber/avx2/kem.c
kybercffi/kyber/avx2/kem.h
kybercffi/kyber/avx2/ntt.S
kybercffi-1.0.1.dist-info/licenses/LICENSE
kybercffi-1.0.1.dist-info/METADATA
kybercffi-1.0.1.dist-info/WHEEL
kybercffi-1.0.1.dist-info/top_level.txt
kybercffi-1.0.1.dist-info/RECORD
