Metadata-Version: 2.4
Name: kybercffi
Version: 1.0.1
Summary: Python CFFI bindings for Kyber post-quantum cryptography
Author-email: Denis Magnitov <pm13.magnitov@gmail.com>
License: MIT
Project-URL: Homepage, https://github.com/Denis872/KyberCFFI
Project-URL: Repository, https://github.com/Denis872/KyberCFFI
Project-URL: Documentation, https://github.com/Denis872/KyberCFFI#readme
Project-URL: Changelog, https://github.com/Denis872/KyberCFFI/blob/main/CHANGELOG.md
Project-URL: Bug Tracker, https://github.com/Denis872/KyberCFFI/issues
Project-URL: Source Code, https://github.com/Denis872/KyberCFFI
Keywords: cryptography,post-quantum,quantum-resistant,kyber,kem,key-encapsulation,cffi,pqcrypto,nist
Classifier: Development Status :: 4 - Beta
Classifier: Intended Audience :: Developers
Classifier: Intended Audience :: Science/Research
Classifier: License :: OSI Approved :: MIT License
Classifier: Operating System :: OS Independent
Classifier: Operating System :: Microsoft :: Windows
Classifier: Operating System :: POSIX :: Linux
Classifier: Operating System :: MacOS
Classifier: Programming Language :: Python :: 3
Classifier: Programming Language :: Python :: 3.8
Classifier: Programming Language :: Python :: 3.9
Classifier: Programming Language :: Python :: 3.10
Classifier: Programming Language :: Python :: 3.11
Classifier: Programming Language :: Python :: 3.12
Classifier: Programming Language :: C
Classifier: Topic :: Security :: Cryptography
Classifier: Topic :: Software Development :: Libraries :: Python Modules
Classifier: Topic :: Scientific/Engineering :: Mathematics
Requires-Python: >=3.8
License-File: LICENSE
Requires-Dist: cffi>=1.15.0
Provides-Extra: dev
Requires-Dist: pytest>=6.0; extra == "dev"
Requires-Dist: pytest-cov; extra == "dev"
Requires-Dist: pytest-benchmark; extra == "dev"
Requires-Dist: black; extra == "dev"
Requires-Dist: flake8; extra == "dev"
Requires-Dist: mypy; extra == "dev"
Requires-Dist: build; extra == "dev"
Requires-Dist: twine; extra == "dev"
Provides-Extra: test
Requires-Dist: pytest>=6.0; extra == "test"
Requires-Dist: pytest-benchmark; extra == "test"
Provides-Extra: docs
Requires-Dist: sphinx; extra == "docs"
Requires-Dist: sphinx-rtd-theme; extra == "docs"
Dynamic: license-file
